{
  "ftbchunks.team_prop_defaults": "Team Property Defaults",
  "ftbchunks.team_prop_defaults.def_allow_explosions": "Allow Explosion Damage",
  "ftbchunks.team_prop_defaults.def_block_edit": "Block Edit Mode",
  "ftbchunks.team_prop_defaults.def_block_edit_interact": "Block Edit/Interact Mode",
  "ftbchunks.team_prop_defaults.def_block_interact": "Block Interact Mode",
  "ftbchunks.team_prop_defaults.def_claim_visibility": "Claim Visibility",
  "ftbchunks.team_prop_defaults.def_entity_attack": "Non-living Entity Attack Mode",
  "ftbchunks.team_prop_defaults.def_entity_interact": "Entity Interact Mode",
  "ftbchunks.team_prop_defaults.def_fake_player_ids": "Allow Fake Players by ID",
  "ftbchunks.team_prop_defaults.def_fake_players": "Allow All Fake Players",
  "ftbchunks.team_prop_defaults.def_mob_griefing": "Allow Mob Griefing Actions",
  "ftbchunks.team_prop_defaults.def_named_fake_players": "Named Fake Players",
  "ftbchunks.team_prop_defaults.def_player_visibility": "Location Visibility",
  "ftbchunks.team_prop_defaults.def_pvp": "Allow PvP Combat"
}