{
  "block.ftbquests.aux_task_screen": "[待翻译] Task Screen",
  "block.ftbquests.barrier": "[待翻译] Quest Barrier",
  "block.ftbquests.barrier.object": "[待翻译] Object ID",
  "block.ftbquests.detector": "[待翻译] Quest Detector",
  "block.ftbquests.detector.notifications": "[待翻译] Notifications",
  "block.ftbquests.detector.player": "[待翻译] Player Detector",
  "block.ftbquests.detector.player.height": "[待翻译] Height",
  "block.ftbquests.detector.player.offset_y": "[待翻译] Offset Y",
  "block.ftbquests.detector.player.radius": "[待翻译] Radius",
  "block.ftbquests.detector.redstone": "[待翻译] Redstone Detector",
  "block.ftbquests.detector.redstone.required_redstone": "[待翻译] Required Redstone Level",
  "block.ftbquests.detector.task": "[待翻译] Task",
  "block.ftbquests.loot_crate_opener": "[待翻译] Loot Crate Opener",
  "block.ftbquests.loot_crate_opener.rightclick": "[待翻译] Stored items: %d",
  "block.ftbquests.loot_crate_storage": "[待翻译] Loot Crate Storage",
  "block.ftbquests.screen.no_permission": "[待翻译] You don't have permission to configure this!",
  "block.ftbquests.screen.text_shadow": "[待翻译] Draw Text Shadows",
  "block.ftbquests.screen_1": "[待翻译] Task Screen (1x1)",
  "block.ftbquests.screen_3": "[待翻译] Task Screen (3x3)",
  "block.ftbquests.screen_5": "[待翻译] Task Screen (5x5)",
  "block.ftbquests.screen_7": "[待翻译] Task Screen (7x7)",
  "block.ftbquests.stage_barrier": "[待翻译] Stage Barrier",
  "commands.ftbquests.change_progress.invalid_type": "[待翻译] Invalid progress type: %s",
  "commands.ftbquests.change_progress.text": "[待翻译] Progress has been changed!",
  "commands.ftbquests.command.delete_empty_reward_tables.text": "[待翻译] Deleted %s empty reward tables",
  "commands.ftbquests.command.error.invalid_id": "[待翻译] Invalid Object ID: %s!",
  "commands.ftbquests.command.error.invalid_type": "[待翻译] Invalid changeProgress type: %s!",
  "commands.ftbquests.command.error.no_file": "[待翻译] No quest file was found, what's going on?!",
  "commands.ftbquests.command.error.no_inventory": "[待翻译] Target block does not contain an inventory!",
  "commands.ftbquests.command.error.no_object": "[待翻译] No quest object found for ID %s!",
  "commands.ftbquests.command.error.not_editing": "[待翻译] You must be in editing mode (/ftbquests editing_mode) to do this!",
  "commands.ftbquests.command.feedback.clear_display_cache": "[待翻译] Item display cache has been cleared for all players",
  "commands.ftbquests.command.feedback.reloaded": "[待翻译] Quest data reloaded from file!",
  "commands.ftbquests.command.feedback.reloaded.disclaimer": "[待翻译] Note: Quest reloading is a quest developer convenience tool and not recommended for use on live servers.",
  "commands.ftbquests.command.feedback.rewards_blocked": "[待翻译] Quest reward blocking for for team '%s' set to: %s",
  "commands.ftbquests.command.feedback.table_exported": "[待翻译] Successfully exported Reward Table '%s' with %s items to the target block!",
  "commands.ftbquests.command.feedback.table_imported": "[待翻译] Successfully imported Reward Table '%s' with %s items!",
  "commands.ftbquests.command.feedback.table_too_many_items": "[待翻译] WARNING: Table %s contains more items than the target block could handle, stopping here!",
  "commands.ftbquests.export_rewards_to_chest.text": "[待翻译] Exported %s / %s items from '%s'",
  "commands.ftbquests.export_rewards_to_chest.usage": "[待翻译] /ftbquests export_rewards_to_chest <reward_table>",
  "commands.ftbquests.locked.disabled": "[待翻译] Unlocked quests for %s",
  "commands.ftbquests.locked.enabled": "[待翻译] Locked quests for %s",
  "commands.ftbquests.weigh_from_emc.invalid_id": "[待翻译] Invalid Reward Table ID!",
  "commands.ftbquests.weigh_from_emc.text": "[待翻译] Changed item reward weight based on EMC in %s",
  "ftbquest.gui.clear_autofocused": "[待翻译] Clear Autofocused Quest",
  "ftbquest.gui.set_autofocused": "[待翻译] Set as Autofocused Quest",
  "ftbquests": "[待翻译] FTB Quests",
  "ftbquests.chapter.appearance.default_min_width": "[待翻译] Default Min Opened Quest Window Width",
  "ftbquests.chapter.appearance.default_quest_shape": "[待翻译] Default Quest Shape",
  "ftbquests.chapter.appearance.default_quest_size": "[待翻译] Default Quest Size",
  "ftbquests.chapter.group": "[待翻译] Group",
  "ftbquests.chapter.image": "[待翻译] Image",
  "ftbquests.chapter.image.align": "[待翻译] Alignment",
  "ftbquests.chapter.image.alpha": "[待翻译] Image Alpha",
  "ftbquests.chapter.image.click": "[待翻译] Click",
  "ftbquests.chapter.image.click.tooltip": "[待翻译] Provide custom functionality when the image is clicked:\n• Open a page or file with http://, https:// or file:/// URL\n• Run a command with 'command:<cmd>'\n• Jump to a quest with '#<quest_id>' (use Copy ID to get quest id's)\n• Fire a CustomClickEvent (for KubeJS or other mods) with 'custom:<resource_location>'",
  "ftbquests.chapter.image.color": "[待翻译] Image Tint",
  "ftbquests.chapter.image.corner": "[待翻译] Rotate and offset from corner",
  "ftbquests.chapter.image.dev": "[待翻译] Only visible in Editing Mode",
  "ftbquests.chapter.image.fit": "[待翻译] Fit to panel width?",
  "ftbquests.chapter.image.height": "[待翻译] Height",
  "ftbquests.chapter.image.hover": "[待翻译] Hover Text",
  "ftbquests.chapter.image.hover.tooltip": "[待翻译] You can use literal text or translation keys here",
  "ftbquests.chapter.image.image": "[待翻译] Image",
  "ftbquests.chapter.image.order": "[待翻译] Image Ordering",
  "ftbquests.chapter.image.order.tooltip": "[待翻译] Order in which images in the same chapter are drawn.\nHigher order images are drawn above lower orders.",
  "ftbquests.chapter.image.rotation": "[待翻译] Rotation",
  "ftbquests.chapter.image.width": "[待翻译] Width",
  "ftbquests.chapter.image.x": "[待翻译] X",
  "ftbquests.chapter.image.y": "[待翻译] Y",
  "ftbquests.chapter.misc.autofocus_id": "[待翻译] Autofocus Quest ID",
  "ftbquests.chapter.misc.autofocus_id.tooltip": "[待翻译] If not empty, must be a Quest or Quest Link ID (use Copy Quest ID to obtain).\nWhen chapter is opened, the panel will automatically center the view on this quest",
  "ftbquests.chapter.misc.consume_items": "[待翻译] Default Item Task 'Consume Items'",
  "ftbquests.chapter.misc.default_repeatable": "[待翻译] Default 'Repeatable Quest'",
  "ftbquests.chapter.misc.progression_mode": "[待翻译] Default 'Progression Mode'",
  "ftbquests.chapter.misc.require_sequential_tasks": "[待翻译] Sequential Task Completion",
  "ftbquests.chapter.misc.require_sequential_tasks.tooltip": "[待翻译] When true, tasks must be completed in the strict order in which they were added to the quest",
  "ftbquests.chapter.subtitle": "[待翻译] Subtitle",
  "ftbquests.chapter.visibility.always_invisible": "[待翻译] Always Invisible",
  "ftbquests.chapter.visibility.default_hide_dependency_lines": "[待翻译] Default 'Hide Dependency Lines'",
  "ftbquests.chapter.visibility.hide_quest_details_until_startable": "[待翻译] Hide Quest Details Until Startable",
  "ftbquests.chapter.visibility.hide_quest_until_deps_complete": "[待翻译] Hide Quests Until Dependencies Complete",
  "ftbquests.chapter.visibility.hide_quest_until_deps_visible": "[待翻译] Hide Quests Until Dependencies Visible",
  "ftbquests.chapter_group": "[待翻译] Chapter Group",
  "ftbquests.chapter_groups": "[待翻译] Chapter Groups",
  "ftbquests.disable_completion_toast": "[待翻译] Disable Completion Toast",
  "ftbquests.file.defaults.autoclaim_rewards": "[待翻译] Reward 'Auto-claim'",
  "ftbquests.file.defaults.consume_items": "[待翻译] Task 'Consume Items'",
  "ftbquests.file.defaults.quest_disable_jei": "[待翻译] Quest 'Disable JEI Recipe'",
  "ftbquests.file.detection_delay": "[待翻译] Item Auto-Detection Minimum Interval",
  "ftbquests.file.detection_delay.tooltip": "[待翻译] Minimum interval (in ticks) between checks of a player's inventory when it changes\nHigher values are kinder on server TPS, especially if players inventories change frequently, but mean longer delays for quest auto-completion messages.",
  "ftbquests.file.disable_gui": "[待翻译] Disable GUI",
  "ftbquests.file.drop_book_on_death": "[待翻译] Drop FTB Quests Book on Death",
  "ftbquests.file.drop_loot_crates": "[待翻译] Entities Drop Loot Crates",
  "ftbquests.file.full_screen_quest_view": "[待翻译] Full Screen Quest View",
  "ftbquests.file.grid_scale": "[待翻译] Grid Scale",
  "ftbquests.file.lock_message": "[待翻译] Lock Message",
  "ftbquests.file.loot_crate_no_drop": "[待翻译] Entity Loot Crate Drop Empty Weight",
  "ftbquests.file.pause_game": "[待翻译] Quest Screen Pauses SSP Game",
  "ftbquests.file.pause_game.tooltip": "[待翻译] Does not apply to multiplayer games",
  "ftbquests.file.progression_mode": "[待翻译] Progression Mode",
  "ftbquests.file.progression_mode.default": "[待翻译] Default",
  "ftbquests.file.progression_mode.flexible": "[待翻译] Flexible",
  "ftbquests.file.progression_mode.linear": "[待翻译] Linear",
  "ftbquests.file.progression_mode.tooltip": "[待翻译] Linear: quest must be complete before dependant quests are started\nFlexible: tasks in dependant quests can be progressed at any time,\n  but dependant quests can't be completed until dependency is completed",
  "ftbquests.gui.add_dependencies": "[待翻译] Add selected as dependencies",
  "ftbquests.gui.add_dependencies_self": "[待翻译] Add as dependency to selected",
  "ftbquests.gui.autopin.off": "[待翻译] Auto-pin: Disabled",
  "ftbquests.gui.autopin.on": "[待翻译] Auto-pin: Enabled",
  "ftbquests.gui.bulk_change_size": "[待翻译] Change Size for all...",
  "ftbquests.gui.change_group": "[待翻译] Change Group",
  "ftbquests.gui.change_progress": "[待翻译] Change Progress",
  "ftbquests.gui.change_progress.complete": "[待翻译] Complete",
  "ftbquests.gui.change_progress.complete_deps": "[待翻译] Complete (+Dependencies)",
  "ftbquests.gui.change_progress.reset": "[待翻译] Reset",
  "ftbquests.gui.change_progress.reset_deps": "[待翻译] Reset (+Dependencies)",
  "ftbquests.gui.clear_formatting": "[待翻译] Clear Formatting",
  "ftbquests.gui.clear_reward_all": "[待翻译] Clear rewards from all",
  "ftbquests.gui.collect_rewards": "[待翻译] Click to collect all rewards!",
  "ftbquests.gui.confirm_esc": "[待翻译] Discard Unsaved Changes?",
  "ftbquests.gui.copy_id.paste_hint": "[待翻译] You can use this ID to paste quests or quest links",
  "ftbquests.gui.copy_id.quick_properties": "[待翻译] Quick Edit Properties...",
  "ftbquests.gui.edit": "[待翻译] Edit",
  "ftbquests.gui.edit_description": "[待翻译] Quest Description Editor",
  "ftbquests.gui.edit_description.help": "[待翻译] Shift+Enter: save & exit",
  "ftbquests.gui.edit_linked_quest": "[待翻译] Edit Linked Quest",
  "ftbquests.gui.edit_quest_props": "[待翻译] Quest Properties",
  "ftbquests.gui.edit_text": "[待翻译] Edit Text",
  "ftbquests.gui.fix_aspect_ratio_h": "[待翻译] Adjust Height to Aspect Ratio",
  "ftbquests.gui.fix_aspect_ratio_w": "[待翻译] Adjust Width to Aspect Ratio",
  "ftbquests.gui.goto_linked_quest": "[待翻译] Go to Linked Quest (in chapter: %s)",
  "ftbquests.gui.image": "[待翻译] Add Image",
  "ftbquests.gui.insert_link": "[待翻译] Insert Link",
  "ftbquests.gui.key_reference.editor": "[待翻译] Editor Mode\nCtrl + Left Mouse;Toggle Selection\nMiddle Mouse;Move Selected Quest(s)\nRight Mouse;Context Menu\nMiddle Mouse: Drag;Select Quests in Drag Box\nCtrl + Middle Mouse: Drag;Toggle Selection in Box\nCtrl + A;Select All\nCtrl + D;Select None\nCtrl + Up/Down/Left/Right;Move Selected Quests\nCtrl + R;Toggle Crosshairs\nCtrl + C;Copy Selected/Hovered Object\nCtrl + V;Paste Selection\nCtrl + Shift + V;Paste Quest (no dependencies)\nCtrl + Alt + V;Paste as Quest Link\n\nQuest View Panel\nT;Edit Quest Title\nS;Edit Quest Subtitle\nD;Edit Quest Description",
  "ftbquests.gui.key_reference.player": "[待翻译] General Controls\n-;Zoom out\n+;Zoom in\n0;Reset Zoom\nTab;Next Chapter\nShift + Tab;Previous Chapter\n1 - 9;Go to Chapter\nSpace;Recenter View\nCtrl + F;Search\nF1;While hovering quest, show extended info\nLeft Mouse;View Quest Details\nMouse Wheel;Scroll Up/Down\nShift + Mouse Wheel;Scroll Left/Right\nCtrl + Mouse Wheel;Zoom In/Out",
  "ftbquests.gui.line": "[待翻译] Add Text Line",
  "ftbquests.gui.linked_quest_id": "[待翻译] Linked Quest ID: %s",
  "ftbquests.gui.move_to_chapter": "[待翻译] Move to another chapter",
  "ftbquests.gui.move_tooltip": "[待翻译] Shortcut: Middle mouse button click",
  "ftbquests.gui.no_dependants": "[待翻译] No Dependants",
  "ftbquests.gui.no_dependencies": "[待翻译] No Dependencies",
  "ftbquests.gui.open_in_guide": "[待翻译] Click here to read more...",
  "ftbquests.gui.page_break": "[待翻译] Add Page Break",
  "ftbquests.gui.paste": "[待翻译] Paste Quest",
  "ftbquests.gui.paste_image": "[待翻译] Paste Image",
  "ftbquests.gui.paste_link": "[待翻译] Paste Quest Link",
  "ftbquests.gui.paste_no_deps": "[待翻译] Paste Quest (no dependencies)",
  "ftbquests.gui.paste_task": "[待翻译] Paste Task",
  "ftbquests.gui.pin": "[待翻译] Pin",
  "ftbquests.gui.preferences": "[待翻译] Player Preferences",
  "ftbquests.gui.reload_theme": "[待翻译] Reload Theme",
  "ftbquests.gui.remove_dependencies": "[待翻译] Remove selected from dependencies",
  "ftbquests.gui.remove_dependencies_self": "[待翻译] Remove as dependency from selected",
  "ftbquests.gui.restore": "[待翻译] Restore",
  "ftbquests.gui.save_on_server": "[待翻译] Save on Server now",
  "ftbquests.gui.saved_on_server": "[待翻译] Quests saved on server",
  "ftbquests.gui.select_reward_table": "[待翻译] Select Reward Table",
  "ftbquests.gui.undo": "[待翻译] Undo",
  "ftbquests.gui.unpin": "[待翻译] Unpin",
  "ftbquests.gui.use_as_quest_icon": "[待翻译] Use Task Icon as Quest Icon",
  "ftbquests.gui.view_dependants": "[待翻译] View Dependants",
  "ftbquests.gui.view_dependencies": "[待翻译] View Dependencies",
  "ftbquests.gui.view_quest_links": "[待翻译] View Quest Link(s)",
  "ftbquests.gui.wiki": "[待翻译] Open Wiki",
  "ftbquests.icon.tooltip": "[待翻译] Custom icon",
  "ftbquests.leaderboard_progress": "[待翻译] FTB Quests Progress",
  "ftbquests.loot.entitydrops": "[待翻译] Entity Drops",
  "ftbquests.loot.entitytype.boss": "[待翻译] Boss",
  "ftbquests.loot.entitytype.monster": "[待翻译] Monster",
  "ftbquests.loot.entitytype.passive": "[待翻译] Passive",
  "ftbquests.message.configurator_bound": "[待翻译] Configurator Bound: %s",
  "ftbquests.message.missing_task_screen": "[待翻译] Task Screen is missing!",
  "ftbquests.message.task_screen_inaccessible": "[待翻译] Task Screen is not accessible from here!",
  "ftbquests.null": "[待翻译] None",
  "ftbquests.objects": "[待翻译] %d object(s)",
  "ftbquests.quest.appearance": "[待翻译] Appearance",
  "ftbquests.quest.appearance.icon_scale": "[待翻译] Icon Scaling",
  "ftbquests.quest.appearance.icon_scale.tooltip": "[待翻译] Independent of the overall button size",
  "ftbquests.quest.appearance.min_width": "[待翻译] Min Opened Quest Window Width",
  "ftbquests.quest.appearance.size": "[待翻译] Size",
  "ftbquests.quest.appearance.size.tooltip": "[待翻译] 0 means to use chapter default",
  "ftbquests.quest.cannot_copy_many": "[待翻译] Copying multiple objects is not supported!",
  "ftbquests.quest.copied": "[待翻译] Copied object:",
  "ftbquests.quest.dependencies": "[待翻译] Dependencies",
  "ftbquests.quest.dependencies.dependency_requirement": "[待翻译] Dependency Requirement",
  "ftbquests.quest.dependencies.hide_dependency_lines": "[待翻译] Hide Dependency Lines",
  "ftbquests.quest.dependencies.hide_dependent_lines": "[待翻译] Hide Dependent Lines",
  "ftbquests.quest.dependencies.hide_dependent_lines.tooltip": "[待翻译] Controls display of dependency lines to quests which are unlocked by this one",
  "ftbquests.quest.dependencies.max_completable_dependents": "[待翻译] Max Completable Dependents",
  "ftbquests.quest.dependencies.max_completable_dependents.tooltip": "[待翻译] If > 0, at most this number of dependents can be completed, and uncompleted dependents become unavailable\nUseful to have exclusive branches in a questline",
  "ftbquests.quest.dependencies.min_required_dependencies": "[待翻译] Min Required Dependencies",
  "ftbquests.quest.dependency_requirement.all_completed": "[待翻译] All Completed",
  "ftbquests.quest.dependency_requirement.all_started": "[待翻译] All Started",
  "ftbquests.quest.dependency_requirement.one_completed": "[待翻译] One Completed",
  "ftbquests.quest.dependency_requirement.one_started": "[待翻译] One Started",
  "ftbquests.quest.dependency_requirement.tooltip": "[待翻译] Ignored if Min Required Dependencies > 0",
  "ftbquests.quest.hidden_quests_footer": "[待翻译] %d hidden",
  "ftbquests.quest.hide_dependency_lines.tooltip": "[待翻译] Controls display of dependency lines from quests which unlock this one",
  "ftbquests.quest.locked": "[待翻译] Locked: uncompleted dependencies",
  "ftbquests.quest.min_required_dependencies.tooltip": "[待翻译] If you set this to anything more than 0, it becomes an OR quest, where only certain amount of dependencies is required for it to unlock",
  "ftbquests.quest.min_required_header": "[待翻译] %d required",
  "ftbquests.quest.misc": "[待翻译] Misc",
  "ftbquests.quest.misc.disable_jei": "[待翻译] Disable JEI Recipe",
  "ftbquests.quest.misc.exclusive": "[待翻译] Exclusive Quest Branch",
  "ftbquests.quest.misc.exclusive.desc": "[待翻译] Completing this makes other branches unavailable",
  "ftbquests.quest.misc.guide_page": "[待翻译] Guide Page",
  "ftbquests.quest.misc.ignore_reward_blocking": "[待翻译] Ignore reward blocking",
  "ftbquests.quest.misc.ignore_reward_blocking.tooltip": "[待翻译] Offer the quest reward(s) even if rewards are blocked for the team by the '/ftbquests block_rewards' command",
  "ftbquests.quest.misc.optional": "[待翻译] Optional Quest",
  "ftbquests.quest.misc.optional_task": "[待翻译] Optional Task",
  "ftbquests.quest.misc.progression_mode": "[待翻译] Progression Mode",
  "ftbquests.quest.misc.require_sequential_tasks": "[待翻译] Sequential Task Completion",
  "ftbquests.quest.misc.require_sequential_tasks.tooltip": "[待翻译] When true, tasks must be completed in the strict order in which they were added to the quest\nDefault means to use chapter setting",
  "ftbquests.quest.shape.circle": "[待翻译] Circle",
  "ftbquests.quest.shape.default": "[待翻译] Default",
  "ftbquests.quest.shape.diamond": "[待翻译] Diamond",
  "ftbquests.quest.shape.gear": "[待翻译] Gear",
  "ftbquests.quest.shape.heart": "[待翻译] Heart",
  "ftbquests.quest.shape.hexagon": "[待翻译] Hexagon",
  "ftbquests.quest.shape.none": "[待翻译] <None>",
  "ftbquests.quest.shape.octagon": "[待翻译] Octagon",
  "ftbquests.quest.shape.pentagon": "[待翻译] Pentagon",
  "ftbquests.quest.shape.rsquare": "[待翻译] Rounded Square",
  "ftbquests.quest.shape.square": "[待翻译] Square",
  "ftbquests.quest.subtitle": "[待翻译] Subtitle",
  "ftbquests.quest.visibility.hide_details_until_startable": "[待翻译] Hide Details Until Startable",
  "ftbquests.quest.visibility.hide_details_until_startable.tooltip": "[待翻译] If true, then quest details (text and tasks) can't be viewed until the quest can be started",
  "ftbquests.quest.visibility.hide_lock_icon": "[待翻译] Hide Lock Icon",
  "ftbquests.quest.visibility.hide_lock_icon.tooltip": "[待翻译] Hide the lock icon that is normally show when quest is locked due to a dependency",
  "ftbquests.quest.visibility.hide_text_until_complete": "[待翻译] Hide Text Until Quest is Completed",
  "ftbquests.quest.visibility.hide_text_until_complete.tooltip": "[待翻译] Quest details can be opened, but no description text is displayed until the quest is completed",
  "ftbquests.quest.visibility.hide_until_deps_complete": "[待翻译] Hide Quest Until Dependencies Complete",
  "ftbquests.quest.visibility.hide_until_deps_visible": "[待翻译] Hide Quest Until Dependencies Visible",
  "ftbquests.quest.visibility.invisible": "[待翻译] Invisible Until Completed",
  "ftbquests.quest.visibility.invisible.tooltip": "[待翻译] Quest is invisible to players until completed.\nUseful for \"easter egg\" optional quests.",
  "ftbquests.quest.visibility.invisible_until_tasks": "[待翻译] Invisible until X tasks are completed",
  "ftbquests.quest.visibility.invisible_until_tasks.tooltip": "[待翻译] Only applies if Invisible is true.\nIf > 0, quest becomes visible if X or more tasks are completed.",
  "ftbquests.quest_link": "[待翻译] Quest Link",
  "ftbquests.quest_link.shape": "[待翻译] Shape",
  "ftbquests.quest_link.size": "[待翻译] Size",
  "ftbquests.quest_link.x": "[待翻译] X",
  "ftbquests.quest_link.y": "[待翻译] Y",
  "ftbquests.raymatcher.block_entity_class": "[待翻译] Block Entity Class",
  "ftbquests.raymatcher.block_entity_id": "[待翻译] Block Entity ID",
  "ftbquests.raymatcher.block_id": "[待翻译] Block ID",
  "ftbquests.raymatcher.entity_class": "[待翻译] Entity Class",
  "ftbquests.raymatcher.entity_id": "[待翻译] Entity ID",
  "ftbquests.reward.autoclaim": "[待翻译] Auto-claim",
  "ftbquests.reward.autoclaim.default": "[待翻译] Default",
  "ftbquests.reward.autoclaim.disabled": "[待翻译] Disabled",
  "ftbquests.reward.autoclaim.enabled": "[待翻译] Enabled",
  "ftbquests.reward.autoclaim.invisible": "[待翻译] Enabled, Invisible",
  "ftbquests.reward.autoclaim.no_toast": "[待翻译] Enabled, No Toast",
  "ftbquests.reward.blocked": "[待翻译] %d reward(s) blocked for team '%s'",
  "ftbquests.reward.exclude_from_claim_all": "[待翻译] Exclude from Claim All",
  "ftbquests.reward.exclude_from_claim_all.tooltip": "[待翻译] Ignore this reward when the \"Claim All\" button is clicked\nThis setting cannot be changed for Loot, Random\n and Choice reward types",
  "ftbquests.reward.ftbquests.advancement": "[待翻译] Advancement",
  "ftbquests.reward.ftbquests.advancement.criterion": "[待翻译] Criterion",
  "ftbquests.reward.ftbquests.advancement.criterion.tooltip": "[待翻译] Optional, set if you want only one criterion to be granted",
  "ftbquests.reward.ftbquests.all_table": "[待翻译] All Table Reward",
  "ftbquests.reward.ftbquests.command.elevate": "[待翻译] Run with Elevated Permission",
  "ftbquests.reward.ftbquests.command.elevate.tooltip": "[待翻译] Run the command as if the player had permission level 2",
  "ftbquests.reward.ftbquests.command.silent": "[待翻译] Silent",
  "ftbquests.reward.ftbquests.command.tooltip": "[待翻译] Vanilla substitutions, e.g. @p, are supported\nSpecial substitutions:\n{x} / {y} / {z} - player's current X/Y/Z pos\n{quest} - ID of this quest\n{chapter} - ID of this chapter\n{team} - short name of player's team",
  "ftbquests.reward.ftbquests.custom": "[待翻译] Custom",
  "ftbquests.reward.ftbquests.gamestage": "[待翻译] Stage",
  "ftbquests.reward.ftbquests.gamestage.remove": "[待翻译] Remove",
  "ftbquests.reward.ftbquests.gamestage.silent": "[待翻译] Silent",
  "ftbquests.reward.ftbquests.item.count": "[待翻译] Count",
  "ftbquests.reward.ftbquests.item.only_one": "[待翻译] Only One",
  "ftbquests.reward.ftbquests.item.only_one.tooltip": "[待翻译] If inventory has that item, doesn't give it. Ignores NBT.",
  "ftbquests.reward.ftbquests.npc_faction": "[待翻译] CustomNPCs Faction",
  "ftbquests.reward.ftbquests.npc_faction.add": "[待翻译] Add",
  "ftbquests.reward.ftbquests.npc_faction.id": "[待翻译] Faction ID",
  "ftbquests.reward.ftbquests.npc_faction.points": "[待翻译] Points",
  "ftbquests.reward.ftbquests.npc_mail": "[待翻译] CustomNPCs Mail",
  "ftbquests.reward.ftbquests.npc_mail.been_read": "[待翻译] Been Read",
  "ftbquests.reward.ftbquests.npc_mail.items": "[待翻译] Items",
  "ftbquests.reward.ftbquests.npc_mail.message": "[待翻译] Message",
  "ftbquests.reward.ftbquests.npc_mail.quest_id": "[待翻译] CustomNPCs Quest ID",
  "ftbquests.reward.ftbquests.npc_mail.quest_title": "[待翻译] CustomNPCs Quest Title",
  "ftbquests.reward.ftbquests.npc_mail.sender": "[待翻译] Sender",
  "ftbquests.reward.ftbquests.npc_mail.subject": "[待翻译] Subject",
  "ftbquests.reward.ftbquests.npc_mail.time": "[待翻译] Time",
  "ftbquests.reward.ftbquests.npc_mail.time_past": "[待翻译] Time Past",
  "ftbquests.reward.ftbquests.npc_quest": "[待翻译] CustomNPCs Quest",
  "ftbquests.reward.ftbquests.npc_quest.id": "[待翻译] Quest ID",
  "ftbquests.reward.ftbquests.toast": "[待翻译] Toast",
  "ftbquests.reward.ftbquests.toast.description": "[待翻译] Description",
  "ftbquests.reward.random_bonus": "[待翻译] Random Bonus",
  "ftbquests.reward.team_reward.tooltip": "[待翻译] When true, this is one reward for the whole team; only the submitting player receives it\nWhen false, all online players receive the reward",
  "ftbquests.reward.this_blocked": "[待翻译] Reward blocked for team '%s'",
  "ftbquests.reward_table.and_more": "[待翻译] ...and %d more",
  "ftbquests.reward_table.disable_loot_crate": "[待翻译] Disable Loot Crate",
  "ftbquests.reward_table.enable_loot_crate": "[待翻译] Enable Loot Crate",
  "ftbquests.reward_table.loot_crate.boss_weight": "[待翻译] Weight (Boss)",
  "ftbquests.reward_table.loot_crate.color": "[待翻译] Color",
  "ftbquests.reward_table.loot_crate.glow": "[待翻译] Glow",
  "ftbquests.reward_table.loot_crate.id": "[待翻译] ID",
  "ftbquests.reward_table.loot_crate.item_name": "[待翻译] Item Name",
  "ftbquests.reward_table.loot_crate.item_name.tooltip": "[待翻译] This may be a translation key",
  "ftbquests.reward_table.loot_crate.monster_weight": "[待翻译] Weight (Monster)",
  "ftbquests.reward_table.loot_crate.passive_weight": "[待翻译] Weight (Passive)",
  "ftbquests.reward_table.used_in": "[待翻译] Used in %d Quest Rewards",
  "ftbquests.tags": "[待翻译] Tags",
  "ftbquests.tags.tooltip": "[待翻译] Used for themes and KubeJS events",
  "ftbquests.task.ftbquests.advancement": "[待翻译] Advancement",
  "ftbquests.task.ftbquests.advancement.criterion": "[待翻译] Criterion",
  "ftbquests.task.ftbquests.biome": "[待翻译] Visit Biome",
  "ftbquests.task.ftbquests.biome.biome": "[待翻译] Biome",
  "ftbquests.task.ftbquests.checkmark": "[待翻译] Checkmark",
  "ftbquests.task.ftbquests.custom": "[待翻译] Custom",
  "ftbquests.task.ftbquests.dimension.dim": "[待翻译] Dimension",
  "ftbquests.task.ftbquests.gamestage": "[待翻译] Stage",
  "ftbquests.task.ftbquests.interaction": "[待翻译] Interaction",
  "ftbquests.task.ftbquests.interaction.match": "[待翻译] Match",
  "ftbquests.task.ftbquests.interaction.properties": "[待翻译] Properties",
  "ftbquests.task.ftbquests.interaction.type": "[待翻译] Type",
  "ftbquests.task.ftbquests.item.click_recipe": "[待翻译] Click to view recipe(s)",
  "ftbquests.task.ftbquests.item.consume_items": "[待翻译] Consume Items",
  "ftbquests.task.ftbquests.item.convert_tag": "[待翻译] Convert to '%s' Tag Filter",
  "ftbquests.task.ftbquests.item.hide_valid_items": "[待翻译] Hide Valid Items",
  "ftbquests.task.ftbquests.item.match_nbt": "[待翻译] Match NBT",
  "ftbquests.task.ftbquests.item.match_nbt.tooltip": "[待翻译] Default: item must be in 'itemfilters:check_nbt' item tag\nFalse: never check NBT\nTrue: always check NBT",
  "ftbquests.task.ftbquests.item.only_from_crafting": "[待翻译] Only Detect From Crafting",
  "ftbquests.task.ftbquests.item.select_tag": "[待翻译] Select an Item Tag",
  "ftbquests.task.ftbquests.item.task_screen_only": "[待翻译] Only From Task Screen",
  "ftbquests.task.ftbquests.item.task_screen_only.tooltip": "[待翻译] When true, items may only be submitted by piping into a Task Screen\nOnly applies when Consume Items is true for this task.",
  "ftbquests.task.ftbquests.item.valid_for": "[待翻译] Valid items for %s",
  "ftbquests.task.ftbquests.item.view_items": "[待翻译] Click to view valid items",
  "ftbquests.task.ftbquests.item.weak_nbt_match": "[待翻译] Weak NBT Match",
  "ftbquests.task.ftbquests.item.weak_nbt_match.tooltip": "[待翻译] False: exact NBT match required\nTrue: NBT fields in the checked item but not in the filter item won't cause a match failure",
  "ftbquests.task.ftbquests.kill.title": "[待翻译] Kill: %sx %s",
  "ftbquests.task.ftbquests.location": "[待翻译] Location",
  "ftbquests.task.ftbquests.location.d": "[待翻译] Z Size (D)",
  "ftbquests.task.ftbquests.location.dim": "[待翻译] Dimension",
  "ftbquests.task.ftbquests.location.h": "[待翻译] Y Size (H)",
  "ftbquests.task.ftbquests.location.ignore_dim": "[待翻译] Ignore Dimension",
  "ftbquests.task.ftbquests.location.w": "[待翻译] X Size (W)",
  "ftbquests.task.ftbquests.location.x": "[待翻译] X Position",
  "ftbquests.task.ftbquests.location.x.tooltip": "[待翻译] Minimum X for player (player-X must be >= X and < X+W)",
  "ftbquests.task.ftbquests.location.y": "[待翻译] Y Position",
  "ftbquests.task.ftbquests.location.y.tooltip": "[待翻译] Minimum Y for player (player-Y must be >= Y and < Y+H)",
  "ftbquests.task.ftbquests.location.z": "[待翻译] Z Position",
  "ftbquests.task.ftbquests.location.z.tooltip": "[待翻译] Minimum Z for player (player-Z must be >= Z and < Z+D)",
  "ftbquests.task.ftbquests.npc_dialog": "[待翻译] CustomNPCs Dialog",
  "ftbquests.task.ftbquests.npc_dialog.id": "[待翻译] Dialog ID",
  "ftbquests.task.ftbquests.npc_faction": "[待翻译] CustomNPCs Faction",
  "ftbquests.task.ftbquests.npc_faction.id": "[待翻译] Faction ID",
  "ftbquests.task.ftbquests.npc_faction.mode": "[待翻译] Point mode",
  "ftbquests.task.ftbquests.npc_faction.required_points": "[待翻译] Required Points",
  "ftbquests.task.ftbquests.npc_quest": "[待翻译] CustomNPCs Quest",
  "ftbquests.task.ftbquests.npc_quest.check_active": "[待翻译] Check if quest is active",
  "ftbquests.task.ftbquests.npc_quest.id": "[待翻译] Quest ID",
  "ftbquests.task.ftbquests.observation": "[待翻译] Observation",
  "ftbquests.task.ftbquests.observation.observe_type": "[待翻译] Type",
  "ftbquests.task.ftbquests.observation.timer": "[待翻译] Timer",
  "ftbquests.task.ftbquests.observation.to_observe": "[待翻译] Observe",
  "ftbquests.task.ftbquests.structure": "[待翻译] Find Structure",
  "ftbquests.task.ftbquests.structure.structure": "[待翻译] Structure",
  "ftbquests.task.ftbquests.tech_reborn_energy": "[待翻译] Tech Reborn Energy",
  "ftbquests.task.ftbquests.tech_reborn_energy.text": "[待翻译] %d E",
  "ftbquests.task.ftbquests.tech_reborn_energy.value": "[待翻译] E",
  "ftbquests.task.ftbquests.xp.points": "[待翻译] Points",
  "ftbquests.task.ftbquests.xp.points.tooltip": "[待翻译] Use XP points to complete instead of levels. Use a calculator to find out what the value should be",
  "ftbquests.task.ftbquests.xp.value": "[待翻译] XP",
  "ftbquests.task.task_screen_only": "[待翻译] Items can ONLY be submitted via a Task Screen!",
  "ftbquests.task_title": "[待翻译] Task Title",
  "ftbquests.title.tooltip": "[待翻译] Custom title",
  "ftbquests.ui.old_scroll_wheel": "[待翻译] Old-style Scroll Wheel Behavior",
  "ftbquests.ui.old_scroll_wheel.tooltip": "[待翻译] When false, scroll wheel scrolls up & down: hold Shift to pan, Ctrl to zoom\nWhen true, scroll wheel only zooms (1.19 and earlier behavior)",
  "ftbquests.ui.pinned_quests_inset_x": "[待翻译] Pinned Quests Panel X Inset",
  "ftbquests.ui.pinned_quests_inset_x.tooltip": "[待翻译] Inset is toward center of screen.\nIgnored if X pos is center.",
  "ftbquests.ui.pinned_quests_inset_y": "[待翻译] Pinned Quests Panel Y Inset",
  "ftbquests.ui.pinned_quests_inset_y.tooltip": "[待翻译] Inset is toward center of screen.\nIgnored if Y pos is center.",
  "ftbquests.ui.pinned_quests_pos": "[待翻译] Pinned Quests Panel Position",
  "ftbquests.ui.show_lock_icon": "[待翻译] Show Icon for Locked Quests",
  "ftbquests.ui.show_lock_icon.tooltip": "[待翻译] Show a padlock icon on any quests which can't yet be started due to dependency restrictions.",
  "item.ftbquests.barrier.config": "[待翻译] Rename in anvil to set the Quest ID",
  "item.ftbquests.barrier.disabled": "[待翻译] Only works in Editing Mode!",
  "item.ftbquests.barrier.nogui": "[待翻译] GUI is still work in progress",
  "item.ftbquests.book.disabled": "[待翻译] Quest Book GUI is disabled!",
  "item.ftbquests.book.tooltip": "[待翻译] Right-click to open quest window",
  "item.ftbquests.custom_icon": "[待翻译] Custom Icon",
  "item.ftbquests.custom_icon.tooltip": "[待翻译] Right-click on 'Icon' in editor to open custom image selector",
  "item.ftbquests.lootcrate.missing": "[待翻译] ERROR: unknown loot crate '%s'!",
  "item.ftbquests.lootcrate.tooltip_1": "[待翻译] Right-click to open",
  "item.ftbquests.lootcrate.tooltip_2": "[待翻译] Sneak-right-click to open all in hand",
  "item.ftbquests.missing_item": "[待翻译] Missing Item",
  "item.ftbquests.stage_barrier.config": "[待翻译] Rename in anvil to set the Stage",
  "item.ftbquests.task_screen_configurator": "[待翻译] Task Screen Configurator",
  "item.ftbquests.task_screen_configurator.tooltip": "[待翻译] Sneak + Right-Click a Task Screen block to bind",
  "itemGroup.ftbquests.ftbquests": "[待翻译] FTB Quests",
  "jei.ftbquests.lootcrates": "[待翻译] Loot Crates",
  "jei.ftbquests.lootcrates.chance": "[待翻译] Chance: %s",
  "jei.ftbquests.lootcrates.dropped_by": "[待翻译] Dropped by:",
  "jei.ftbquests.lootcrates.no_chance": "[待翻译] No item chance: %s",
  "key.categories.ftbquests": "[待翻译] FTB Quests"
}